jsonfaker/__init__.py
jsonfaker/utils.py
jsonfaker-0.0.1.dist-info/LICENSE.txt
jsonfaker-0.0.1.dist-info/METADATA
jsonfaker-0.0.1.dist-info/WHEEL
jsonfaker-0.0.1.dist-info/top_level.txt
jsonfaker-0.0.1.dist-info/RECORD
