Metadata-Version: 2.1
Name: jsonfaker
Version: 0.0.1
Summary: A simple faked JSON generator
Home-page: https://github.com/acegik/jsonfaker
Author: acegik
License: GPL-3.0
Download-URL: https://github.com/acegik/jsonfaker/downloads
Keywords: sysops,devops,tools
Platform: UNKNOWN
Requires-Python: >=2.7,!=3.0.*,!=3.1.*,!=3.2.*,!=3.3.*
Requires-Dist: shortuuid (<2,>=1)
